binsmooth.py
binsmooth-2023.10.0.dist-info/LICENSE
binsmooth-2023.10.0.dist-info/WHEEL
binsmooth-2023.10.0.dist-info/METADATA
binsmooth-2023.10.0.dist-info/RECORD
