Metadata-Version: 2.1
Name: binsmooth
Version: 2023.10.0
Summary: binsmooth - Better Estimates from Binned Income Data.
Home-page: http://github.com/sjtrny/binsmooth
Author: Stephen Tierney
Author-email: sjtrny@gmail.com
Requires-Python: >=3.9
Classifier: License :: OSI Approved :: MIT License
Requires-Dist: numdifftools == 0.9.41
Requires-Dist: numpy >= 1.25.2
Requires-Dist: scipy >= 1.11.2
Requires-Dist: splines==0.3.0
